sensirion_i2c_sht/__init__.py
sensirion_i2c_sht/version.py
sensirion_i2c_sht/sht2x/__init__.py
sensirion_i2c_sht/sht2x/commands.py
sensirion_i2c_sht/sht2x/device.py
sensirion_i2c_sht/sht2x/response_types.py
sensirion_i2c_sht/sht3x/__init__.py
sensirion_i2c_sht/sht3x/commands.py
sensirion_i2c_sht/sht3x/data_types.py
sensirion_i2c_sht/sht3x/device.py
sensirion_i2c_sht/sht3x/response_types.py
sensirion_i2c_sht/sht4x/__init__.py
sensirion_i2c_sht/sht4x/commands.py
sensirion_i2c_sht/sht4x/data_types.py
sensirion_i2c_sht/sht4x/device.py
sensirion_i2c_sht/sht4x/response_types.py
sensirion_i2c_sht/shtc3/__init__.py
sensirion_i2c_sht/shtc3/commands.py
sensirion_i2c_sht/shtc3/data_types.py
sensirion_i2c_sht/shtc3/device.py
sensirion_i2c_sht/shtc3/response_types.py
sensirion_i2c_sht/sts4x/__init__.py
sensirion_i2c_sht/sts4x/commands.py
sensirion_i2c_sht/sts4x/data_types.py
sensirion_i2c_sht/sts4x/device.py
sensirion_i2c_sht/sts4x/response_types.py
sensirion_i2c_sht-0.4.0.dist-info/LICENSE
sensirion_i2c_sht-0.4.0.dist-info/METADATA
sensirion_i2c_sht-0.4.0.dist-info/WHEEL
sensirion_i2c_sht-0.4.0.dist-info/top_level.txt
sensirion_i2c_sht-0.4.0.dist-info/RECORD
